LICENSE
README.md
setup.py
Tinycord.egg-info/PKG-INFO
Tinycord.egg-info/SOURCES.txt
Tinycord.egg-info/dependency_links.txt
Tinycord.egg-info/requires.txt
Tinycord.egg-info/top_level.txt
tinycord/__init__.py
tinycord/client.py
tinycord/exceptions.py
tinycord/intents.py
tinycord/plugin.py
tinycord/tools.py
tinycord/api/__init__.py
tinycord/api/api.py
tinycord/api/channel.py
tinycord/api/guild.py
tinycord/api/user.py
tinycord/api/utils.py
tinycord/api/webhook.py
tinycord/core/__init__.py
tinycord/core/dispatch.py
tinycord/core/gateway.py
tinycord/core/http.py
tinycord/core/ratelimit.py
tinycord/core/router.py
tinycord/ext/__init__.py
tinycord/ext/commands/__init__.py
tinycord/ext/commands/base.py
tinycord/ext/commands/command_client.py
tinycord/ext/commands/context.py
tinycord/ext/commands/exceptions.py
tinycord/ext/commands/plugin.py
tinycord/ext/commands/utils.py
tinycord/middleware/__init__.py
tinycord/middleware/_base.py
tinycord/middleware/channel_create.py
tinycord/middleware/channel_delete.py
tinycord/middleware/channel_pins_update.py
tinycord/middleware/channel_update.py
tinycord/middleware/guild_ban_add.py
tinycord/middleware/guild_ban_remove.py
tinycord/middleware/guild_create.py
tinycord/middleware/guild_delete.py
tinycord/middleware/guild_emojis_update.py
tinycord/middleware/guild_member_add.py
tinycord/middleware/guild_member_delete.py
tinycord/middleware/guild_member_update.py
tinycord/middleware/guild_role_create.py
tinycord/middleware/guild_role_delete.py
tinycord/middleware/guild_role_update.py
tinycord/middleware/guild_scheduled_event_create.py
tinycord/middleware/guild_scheduled_event_delete.py
tinycord/middleware/guild_scheduled_event_update.py
tinycord/middleware/guild_scheduled_event_user_add.py
tinycord/middleware/guild_scheduled_event_user_remove.py
tinycord/middleware/guild_stickers_update.py
tinycord/middleware/guild_update.py
tinycord/middleware/integration_create.py
tinycord/middleware/integration_delete.py
tinycord/middleware/integration_update.py
tinycord/middleware/invite_create.py
tinycord/middleware/invite_remove.py
tinycord/middleware/message_create.py
tinycord/middleware/message_delete.py
