Metadata-Version: 2.1
Name: Tinycord
Version: 0.3.0
Summary: Easy and flexible Discord wrapper built on aiohttp
Home-page: https://github.com/tinycord/Tinycord
Author: xArty
Author-email: email@xarty.xyz
License: UNKNOWN
Platform: UNKNOWN
Classifier: Programming Language :: Python :: 3
Classifier: License :: OSI Approved :: MIT License
Classifier: Intended Audience :: Developers
Classifier: Operating System :: Microsoft :: Windows
Classifier: Operating System :: MacOS
Classifier: Operating System :: Unix
Requires-Python: >=3.6
License-File: LICENSE
